__init__.py
cli.py
git_tools/__init__.py
git_tools/formatter.py
git_tools/repository.py
git_tools/scanner.py
gitskan-0.1.1.dist-info/licenses/LICENSE
utils/__init__.py
utils/print.py
utils/validation.py
utils/version.py
gitskan-0.1.1.dist-info/METADATA
gitskan-0.1.1.dist-info/WHEEL
gitskan-0.1.1.dist-info/entry_points.txt
gitskan-0.1.1.dist-info/top_level.txt
gitskan-0.1.1.dist-info/RECORD
